<image>
  <name>NVR_ch1_main_20190604160000_20190604162612_134.jpg</name>
  <boxList>
    <box>
      <label>脸</label>
      <xtl>711.01</xtl>
      <ytl>211.34</ytl>
      <xbr>731.24</xbr>
      <ybr>234.29</ybr>
    </box>
    <box>
      <label>脸</label>
      <xtl>1413.17</xtl>
      <ytl>230.36</ytl>
      <xbr>1431.75</xbr>
      <ybr>252.22</ybr>
    </box>
    <box>
      <label>上半身</label>
      <xtl>569.16</xtl>
      <ytl>263.54</ytl>
      <xbr>641.86</xbr>
      <ybr>330.83</ybr>
    </box>
    <box>
      <label>上半身</label>
      <xtl>799.03</xtl>
      <ytl>256.29</ytl>
      <xbr>993.20</xbr>
      <ybr>421.90</ybr>
    </box>
    <box>
      <label>脸</label>
      <xtl>963.29</xtl>
      <ytl>199.61</ytl>
      <xbr>984.80</xbr>
      <ybr>225.23</ybr>
    </box>
    <box>
      <label>上半身</label>
      <xtl>904.64</xtl>
      <ytl>237.92</ytl>
      <xbr>982.05</xbr>
      <ybr>333.04</ybr>
    </box>
    <box>
      <label>上半身</label>
      <xtl>520.86</xtl>
      <ytl>455.69</ytl>
      <xbr>723.00</xbr>
      <ybr>660.66</ybr>
    </box>
    <box>
      <label>脸</label>
      <xtl>89.49</xtl>
      <ytl>564.08</ytl>
      <xbr>127.21</xbr>
      <ybr>619.84</ybr>
    </box>
    <box>
      <label>上半身</label>
      <xtl>0.00</xtl>
      <ytl>666.71</ytl>
      <xbr>214.53</xbr>
      <ybr>962.60</ybr>
    </box>
    <box>
      <label>脸</label>
      <xtl>1165.63</xtl>
      <ytl>281.76</ytl>
      <xbr>1202.84</xbr>
      <ybr>326.93</ybr>
    </box>
    <box>
      <label>脸</label>
      <xtl>910.46</xtl>
      <ytl>261.29</ytl>
      <xbr>943.52</xbr>
      <ybr>289.63</ybr>
    </box>
    <box>
      <label>上半身</label>
      <xtl>674.73</xtl>
      <ytl>325.89</ytl>
      <xbr>759.35</xbr>
      <ybr>405.92</ybr>
    </box>
    <box>
      <label>脸</label>
      <xtl>1603.46</xtl>
      <ytl>325.60</ytl>
      <xbr>1632.59</xbr>
      <ybr>362.60</ybr>
    </box>
    <box>
      <label>脸</label>
      <xtl>817.53</xtl>
      <ytl>526.42</ytl>
      <xbr>875.26</xbr>
      <ybr>571.02</ybr>
    </box>
    <box>
      <label>上半身</label>
      <xtl>1090.80</xtl>
      <ytl>244.62</ytl>
      <xbr>1177.39</xbr>
      <ybr>349.57</ybr>
    </box>
    <box>
      <label>脸</label>
      <xtl>483.62</xtl>
      <ytl>274.20</ytl>
      <xbr>506.57</xbr>
      <ybr>301.53</ybr>
    </box>
    <box>
      <label>脸</label>
      <xtl>413.10</xtl>
      <ytl>421.79</ytl>
      <xbr>443.16</xbr>
      <ybr>449.67</ybr>
    </box>
    <box>
      <label>脸</label>
      <xtl>10.66</xtl>
      <ytl>701.62</ytl>
      <xbr>67.34</xbr>
      <ybr>775.62</ybr>
    </box>
    <box>
      <label>上半身</label>
      <xtl>515.05</xtl>
      <ytl>291.40</ytl>
      <xbr>610.30</xbr>
      <ybr>406.30</ybr>
    </box>
    <box>
      <label>脸</label>
      <xtl>1216.11</xtl>
      <ytl>374.45</ytl>
      <xbr>1259.29</xbr>
      <ybr>424.74</ybr>
    </box>
    <box>
      <label>上半身</label>
      <xtl>1452.17</xtl>
      <ytl>435.41</ytl>
      <xbr>1610.39</xbr>
      <ybr>645.40</ybr>
    </box>
    <box>
      <label>上半身</label>
      <xtl>800.35</xtl>
      <ytl>232.68</ytl>
      <xbr>889.56</xbr>
      <ybr>304.18</ybr>
    </box>
    <box>
      <label>上半身</label>
      <xtl>1436.62</xtl>
      <ytl>228.94</ytl>
      <xbr>1516.43</xbr>
      <ybr>305.47</ybr>
    </box>
    <box>
      <label>脸</label>
      <xtl>1234.42</xtl>
      <ytl>201.16</ytl>
      <xbr>1260.04</xbr>
      <ybr>227.73</ybr>
    </box>
    <box>
      <label>脸</label>
      <xtl>1627.45</xtl>
      <ytl>294.86</ytl>
      <xbr>1653.69</xbr>
      <ybr>329.85</ybr>
    </box>
    <box>
      <label>上半身</label>
      <xtl>312.61</xtl>
      <ytl>356.46</ytl>
      <xbr>397.62</xbr>
      <ybr>469.81</ybr>
    </box>
    <box>
      <label>上半身</label>
      <xtl>737.17</xtl>
      <ytl>465.13</ytl>
      <xbr>977.10</xbr>
      <ybr>670.11</ybr>
    </box>
    <box>
      <label>上半身</label>
      <xtl>635.92</xtl>
      <ytl>230.54</ytl>
      <xbr>697.87</xbr>
      <ybr>294.32</ybr>
    </box>
    <box>
      <label>脸</label>
      <xtl>1398.52</xtl>
      <ytl>200.16</ytl>
      <xbr>1418.11</xbr>
      <ybr>222.02</ybr>
    </box>
    <box>
      <label>脸</label>
      <xtl>945.39</xtl>
      <ytl>231.72</ytl>
      <xbr>970.82</xbr>
      <ybr>262.09</ybr>
    </box>
    <box>
      <label>上半身</label>
      <xtl>565.88</xtl>
      <ytl>218.71</ytl>
      <xbr>625.47</xbr>
      <ybr>276.71</ybr>
    </box>
    <box>
      <label>脸</label>
      <xtl>1125.11</xtl>
      <ytl>265.54</ytl>
      <xbr>1156.28</xbr>
      <ybr>302.38</ybr>
    </box>
    <box>
      <label>脸</label>
      <xtl>412.55</xtl>
      <ytl>355.10</ytl>
      <xbr>441.52</xbr>
      <ybr>380.79</ybr>
    </box>
    <box>
      <label>脸</label>
      <xtl>306.43</xtl>
      <ytl>466.00</ytl>
      <xbr>337.86</xbr>
      <ybr>500.17</ybr>
    </box>
    <box>
      <label>上半身</label>
      <xtl>1308.91</xtl>
      <ytl>312.61</ytl>
      <xbr>1427.77</xbr>
      <ybr>388.97</ybr>
    </box>
    <box>
      <label>上半身</label>
      <xtl>1377.58</xtl>
      <ytl>212.54</ytl>
      <xbr>1463.40</xbr>
      <ybr>271.03</ybr>
    </box>
    <box>
      <label>上半身</label>
      <xtl>1221.34</xtl>
      <ytl>222.31</ytl>
      <xbr>1284.31</xbr>
      <ybr>292.50</ybr>
    </box>
    <box>
      <label>上半身</label>
      <xtl>616.61</xtl>
      <ytl>344.65</ytl>
      <xbr>734.68</xbr>
      <ybr>499.72</ybr>
    </box>
    <box>
      <label>脸</label>
      <xtl>525.16</xtl>
      <ytl>310.82</ytl>
      <xbr>554.68</xbr>
      <ybr>346.90</ybr>
    </box>
    <box>
      <label>上半身</label>
      <xtl>1873.11</xtl>
      <ytl>483.12</ytl>
      <xbr>1918.37</xbr>
      <ybr>639.90</ybr>
    </box>
    <box>
      <label>上半身</label>
      <xtl>604.48</xtl>
      <ytl>205.94</ytl>
      <xbr>655.50</xbr>
      <ybr>263.80</ybr>
    </box>
    <box>
      <label>脸</label>
      <xtl>1142.05</xtl>
      <ytl>207.80</ytl>
      <xbr>1165.81</xbr>
      <ybr>244.50</ybr>
    </box>
    <box>
      <label>脸</label>
      <xtl>1336.91</xtl>
      <ytl>331.27</ytl>
      <xbr>1371.89</xbr>
      <ybr>373.91</ybr>
    </box>
    <box>
      <label>脸</label>
      <xtl>1755.39</xtl>
      <ytl>407.46</ytl>
      <xbr>1780.58</xbr>
      <ybr>447.61</ybr>
    </box>
    <box>
      <label>脸</label>
      <xtl>1118.50</xtl>
      <ytl>205.09</ytl>
      <xbr>1137.39</xbr>
      <ybr>232.48</ybr>
    </box>
    <box>
      <label>上半身</label>
      <xtl>1148.33</xtl>
      <ytl>338.59</ytl>
      <xbr>1287.66</xbr>
      <ybr>476.34</ybr>
    </box>
    <box>
      <label>脸</label>
      <xtl>690.66</xtl>
      <ytl>342.34</ytl>
      <xbr>726.93</xbr>
      <ybr>392.21</ybr>
    </box>
    <box>
      <label>脸</label>
      <xtl>1895.41</xtl>
      <ytl>500.18</ytl>
      <xbr>1919.02</xbr>
      <ybr>556.59</ybr>
    </box>
    <box>
      <label>上半身</label>
      <xtl>1081.78</xtl>
      <ytl>171.33</ytl>
      <xbr>1189.21</xbr>
      <ybr>246.49</ybr>
    </box>
    <box>
      <label>脸</label>
      <xtl>1285.21</xtl>
      <ytl>260.12</ytl>
      <xbr>1310.27</xbr>
      <ybr>292.77</ybr>
    </box>
    <box>
      <label>脸</label>
      <xtl>1536.56</xtl>
      <ytl>468.07</ytl>
      <xbr>1570.40</xbr>
      <ybr>522.39</ybr>
    </box>
    <box>
      <label>脸</label>
      <xtl>866.48</xtl>
      <ytl>279.61</ytl>
      <xbr>905.83</xbr>
      <ybr>327.17</ybr>
    </box>
    <box>
      <label>上半身</label>
      <xtl>176.90</xtl>
      <ytl>481.70</ytl>
      <xbr>274.99</xbr>
      <ybr>564.69</ybr>
    </box>
    <box>
      <label>上半身</label>
      <xtl>385.82</xtl>
      <ytl>391.88</ytl>
      <xbr>495.23</xbr>
      <ybr>475.32</ybr>
    </box>
    <box>
      <label>脸</label>
      <xtl>853.61</xtl>
      <ytl>368.99</ytl>
      <xbr>892.97</xbr>
      <ybr>429.33</ybr>
    </box>
    <box>
      <label>上半身</label>
      <xtl>683.75</xtl>
      <ytl>194.10</ytl>
      <xbr>751.62</xbr>
      <ybr>262.88</ybr>
    </box>
    <box>
      <label>上半身</label>
      <xtl>1548.73</xtl>
      <ytl>246.54</ytl>
      <xbr>1617.06</xbr>
      <ybr>309.40</ybr>
    </box>
    <box>
      <label>上半身</label>
      <xtl>1112.10</xtl>
      <ytl>264.95</ytl>
      <xbr>1250.47</xbr>
      <ybr>403.50</ybr>
    </box>
    <box>
      <label>上半身</label>
      <xtl>461.48</xtl>
      <ytl>261.96</ytl>
      <xbr>536.37</xbr>
      <ybr>338.43</ybr>
    </box>
    <box>
      <label>上半身</label>
      <xtl>1371.88</xtl>
      <ytl>341.74</ytl>
      <xbr>1505.70</xbr>
      <ybr>477.91</ybr>
    </box>
    <box>
      <label>上半身</label>
      <xtl>1094.97</xtl>
      <ytl>202.97</ytl>
      <xbr>1181.89</xbr>
      <ybr>288.25</ybr>
    </box>
    <box>
      <label>脸</label>
      <xtl>1575.52</xtl>
      <ytl>257.69</ytl>
      <xbr>1598.48</xbr>
      <ybr>288.85</ybr>
    </box>
    <box>
      <label>脸</label>
      <xtl>1138.82</xtl>
      <ytl>185.95</ytl>
      <xbr>1154.01</xbr>
      <ybr>203.66</ybr>
    </box>
    <box>
      <label>上半身</label>
      <xtl>1691.08</xtl>
      <ytl>380.86</ytl>
      <xbr>1794.19</xbr>
      <ybr>504.44</ybr>
    </box>
    <box>
      <label>上半身</label>
      <xtl>766.56</xtl>
      <ytl>348.19</ytl>
      <xbr>952.86</xbr>
      <ybr>497.09</ybr>
    </box>
    <box>
      <label>上半身</label>
      <xtl>1202.76</xtl>
      <ytl>384.18</ytl>
      <xbr>1388.84</xbr>
      <ybr>677.60</ybr>
    </box>
    <box>
      <label>脸</label>
      <xtl>327.82</xtl>
      <ytl>373.14</ytl>
      <xbr>353.52</xbr>
      <ybr>411.41</ybr>
    </box>
    <box>
      <label>脸</label>
      <xtl>583.65</xtl>
      <ytl>276.38</ytl>
      <xbr>610.98</xbr>
      <ybr>303.17</ybr>
    </box>
    <box>
      <label>脸</label>
      <xtl>1520.31</xtl>
      <ytl>282.29</ytl>
      <xbr>1544.91</xbr>
      <ybr>313.45</ybr>
    </box>
    <box>
      <label>上半身</label>
      <xtl>924.42</xtl>
      <ytl>220.63</ytl>
      <xbr>991.66</xbr>
      <ybr>287.32</ybr>
    </box>
    <box>
      <label>脸</label>
      <xtl>648.70</xtl>
      <ytl>251.79</ytl>
      <xbr>670.56</xbr>
      <ybr>273.11</ybr>
    </box>
    <box>
      <label>脸</label>
      <xtl>868.70</xtl>
      <ytl>214.16</ytl>
      <xbr>891.79</xbr>
      <ybr>231.88</ybr>
    </box>
    <box>
      <label>上半身</label>
      <xtl>1577.07</xtl>
      <ytl>307.52</ytl>
      <xbr>1670.22</xbr>
      <ybr>415.10</ybr>
    </box>
    <box>
      <label>上半身</label>
      <xtl>1460.67</xtl>
      <ytl>136.01</ytl>
      <xbr>1531.73</xbr>
      <ybr>269.20</ybr>
    </box>
    <box>
      <label>上半身</label>
      <xtl>1202.66</xtl>
      <ytl>184.93</ytl>
      <xbr>1265.52</xbr>
      <ybr>263.10</ybr>
    </box>
    <box>
      <label>上半身</label>
      <xtl>404.71</xtl>
      <ytl>325.76</ytl>
      <xbr>485.79</xbr>
      <ybr>401.32</ybr>
    </box>
    <box>
      <label>上半身</label>
      <xtl>1590.84</xtl>
      <ytl>276.50</ytl>
      <xbr>1678.74</xbr>
      <ybr>347.53</ybr>
    </box>
    <box>
      <label>上半身</label>
      <xtl>836.41</xtl>
      <ytl>191.11</ytl>
      <xbr>915.13</xbr>
      <ybr>253.43</ybr>
    </box>
    <box>
      <label>脸</label>
      <xtl>639.11</xtl>
      <ytl>370.95</ytl>
      <xbr>679.78</xbr>
      <ybr>419.49</ybr>
    </box>
    <box>
      <label>脸</label>
      <xtl>1483.25</xtl>
      <ytl>145.49</ytl>
      <xbr>1505.11</xbr>
      <ybr>171.46</ybr>
    </box>
    <box>
      <label>上半身</label>
      <xtl>1771.90</xtl>
      <ytl>356.79</ytl>
      <xbr>1907.51</xbr>
      <ybr>753.00</ybr>
    </box>
    <box>
      <label>脸</label>
      <xtl>1477.12</xtl>
      <ytl>250.04</ytl>
      <xbr>1498.99</xbr>
      <ybr>277.92</ybr>
    </box>
    <box>
      <label>脸</label>
      <xtl>1234.68</xtl>
      <ytl>233.42</ytl>
      <xbr>1259.24</xbr>
      <ybr>265.54</ybr>
    </box>
    <box>
      <label>脸</label>
      <xtl>209.40</xtl>
      <ytl>533.42</ytl>
      <xbr>254.50</xbr>
      <ybr>599.02</ybr>
    </box>
    <box>
      <label>上半身</label>
      <xtl>947.38</xtl>
      <ytl>187.10</ytl>
      <xbr>1020.63</xbr>
      <ybr>258.35</ybr>
    </box>
    <box>
      <label>脸</label>
      <xtl>1700.29</xtl>
      <ytl>336.62</ytl>
      <xbr>1724.69</xbr>
      <ybr>369.68</ybr>
    </box>
    <box>
      <label>上半身</label>
      <xtl>1490.79</xtl>
      <ytl>259.66</ytl>
      <xbr>1585.90</xbr>
      <ybr>350.40</ybr>
    </box>
    <box>
      <label>上半身</label>
      <xtl>745.90</xtl>
      <ytl>262.20</ytl>
      <xbr>824.62</xbr>
      <ybr>341.57</ybr>
    </box>
    <box>
      <label>脸</label>
      <xtl>576.79</xtl>
      <ytl>489.03</ytl>
      <xbr>636.49</xbr>
      <ybr>555.93</ybr>
    </box>
    <box>
      <label>脸</label>
      <xtl>1430.29</xtl>
      <ytl>380.70</ytl>
      <xbr>1471.22</xbr>
      <ybr>417.70</ybr>
    </box>
    <box>
      <label>上半身</label>
      <xtl>1257.68</xtl>
      <ytl>245.27</ytl>
      <xbr>1338.36</xbr>
      <ybr>341.04</ybr>
    </box>
    <box>
      <label>上半身</label>
      <xtl>133.70</xtl>
      <ytl>505.18</ytl>
      <xbr>337.33</xbr>
      <ybr>750.00</ybr>
    </box>
    <box>
      <label>上半身</label>
      <xtl>62.46</xtl>
      <ytl>545.80</ytl>
      <xbr>186.20</xbr>
      <ybr>703.54</ybr>
    </box>
    <box>
      <label>上半身</label>
      <xtl>291.04</xtl>
      <ytl>423.05</ytl>
      <xbr>409.12</xbr>
      <ybr>549.78</ybr>
    </box>
    <box>
      <label>上半身</label>
      <xtl>1666.28</xtl>
      <ytl>311.46</ytl>
      <xbr>1752.87</xbr>
      <ybr>403.95</ybr>
    </box>
    <box>
      <label>上半身</label>
      <xtl>1390.80</xtl>
      <ytl>192.30</ytl>
      <xbr>1462.86</xbr>
      <ybr>252.99</ybr>
    </box>
    <box>
      <label>脸</label>
      <xtl>776.08</xtl>
      <ytl>282.97</ytl>
      <xbr>801.90</xbr>
      <ybr>314.86</ybr>
    </box>
    <box>
      <label>脸</label>
      <xtl>1324.63</xtl>
      <ytl>424.51</ytl>
      <xbr>1373.37</xbr>
      <ybr>503.86</ybr>
    </box>
    <box>
      <label>脸</label>
      <xtl>580.37</xtl>
      <ytl>229.38</ytl>
      <xbr>602.78</xbr>
      <ybr>255.07</ybr>
    </box>
  </boxList>
</image>